parallels_docker_port_forwarding/__init__.py
parallels_docker_port_forwarding/main.py
parallels_docker_port_forwarding-0.1.3.dist-info/METADATA
parallels_docker_port_forwarding-0.1.3.dist-info/WHEEL
parallels_docker_port_forwarding-0.1.3.dist-info/entry_points.txt
parallels_docker_port_forwarding-0.1.3.dist-info/RECORD
