Metadata-Version: 2.1
Name: parallels-docker-port-forwarding
Version: 0.1.3
Summary: A Docker container port forwarding service for Parallels
Home-page: https://github.com/imtpot/parallels-docker-port-forwarding
License: MIT
Author: imtpot
Author-email: muse-buzz.0@icloud.com
Requires-Python: >=3.9,<4.0
Classifier: License :: OSI Approved :: MIT License
Classifier: Programming Language :: Python :: 3
Classifier: Programming Language :: Python :: 3.9
Classifier: Programming Language :: Python :: 3.10
Classifier: Programming Language :: Python :: 3.11
Classifier: Programming Language :: Python :: 3.12
Requires-Dist: docker (>=7.1.0,<8.0.0)
Project-URL: Repository, https://github.com/imtpot/parallels-docker-port-forwarding
